sphinx_autobuild/__init__.py
sphinx_autobuild/__main__.py
sphinx_autobuild/build.py
sphinx_autobuild/filter.py
sphinx_autobuild/middleware.py
sphinx_autobuild/server.py
sphinx_autobuild/utils.py
sphinx_autobuild-2024.10.2.dist-info/entry_points.txt
sphinx_autobuild-2024.10.2.dist-info/LICENSE.rst
sphinx_autobuild-2024.10.2.dist-info/WHEEL
sphinx_autobuild-2024.10.2.dist-info/METADATA
sphinx_autobuild-2024.10.2.dist-info/RECORD
