Metadata-Version: 2.1
Name: sphinx-autobuild
Version: 2024.10.2
Summary: Rebuild Sphinx documentation on changes, with hot reloading in the browser.
Author: Adam Turner
Author-email: Jonathan Stoppani <jonathan@stoppani.name>
Requires-Python: >=3.9
Classifier: Development Status :: 5 - Production/Stable
Classifier: Environment :: Console
Classifier: Environment :: Web Environment
Classifier: Framework :: Sphinx
Classifier: Intended Audience :: Developers
Classifier: License :: OSI Approved :: MIT License
Classifier: Operating System :: OS Independent
Classifier: Programming Language :: Python
Classifier: Programming Language :: Python :: 3 :: Only
Classifier: Programming Language :: Python :: 3.9
Classifier: Programming Language :: Python :: 3.10
Classifier: Programming Language :: Python :: 3.11
Classifier: Programming Language :: Python :: 3.12
Classifier: Programming Language :: Python :: 3.13
Classifier: Programming Language :: Python :: Implementation :: CPython
Classifier: Programming Language :: Python :: Implementation :: PyPy
Classifier: Topic :: Documentation
Classifier: Topic :: Documentation :: Sphinx
Classifier: Topic :: Software Development
Classifier: Topic :: Software Development :: Documentation
Classifier: Topic :: Software Development :: Libraries :: Python Modules
Classifier: Topic :: Utilities
Requires-Dist: colorama>=0.4.6
Requires-Dist: sphinx
Requires-Dist: starlette>=0.35
Requires-Dist: uvicorn>=0.25
Requires-Dist: watchfiles>=0.20
Requires-Dist: websockets>=11
Requires-Dist: httpx ; extra == "test"
Requires-Dist: pytest>=6 ; extra == "test"
Project-URL: Changelog, https://github.com/sphinx-doc/sphinx-autobuild/blob/main/NEWS.rst
Project-URL: Documentation, https://github.com/sphinx-doc/sphinx-autobuild#readme
Project-URL: Download, https://pypi.org/project/sphinx-autobuild/
Project-URL: Issue tracker, https://github.com/sphinx-doc/sphinx-autobuild/issues
Project-URL: Source, https://github.com/sphinx-doc/sphinx-autobuild
Provides-Extra: docs
Provides-Extra: test
